konnect-stubs/curl/__init__.pyi
konnect-stubs/curl/_enums.pyi
konnect-stubs/curl/_exceptions.pyi
konnect-stubs/curl/_multi.pyi
konnect-stubs/curl/abc.pyi
konnect-stubs/curl/certificates/__init__.pyi
konnect-stubs/curl/certificates/ascii_armor.pyi
konnect-stubs/curl/certificates/configure.pyi
konnect-stubs/curl/certificates/detect.pyi
konnect-stubs/curl/certificates/encodings.pyi
konnect-stubs/curl/certificates/files.pyi
konnect-stubs/curl/requests.pyi
types_konnect_curl-0.2.3.dist-info/METADATA
types_konnect_curl-0.2.3.dist-info/WHEEL
types_konnect_curl-0.2.3.dist-info/licenses/LICENCE.txt
types_konnect_curl-0.2.3.dist-info/RECORD
