Metadata-Version: 2.4
Name: types-konnect.curl
Version: 0.2.3
Summary: static type stubs for konnect.curl
License: MPL-2.0
License-File: LICENCE.txt
Author: Dom Sekotill
Author-email: dom.sekotill@kodo.org.uk
Requires-Python: >=3.11,<4.0
Classifier: License :: OSI Approved
Classifier: Programming Language :: Python :: 3
Classifier: Programming Language :: Python :: 3.11
Classifier: Programming Language :: Python :: 3.12
Classifier: Programming Language :: Python :: 3.13
Classifier: Programming Language :: Python :: 3.14
